{
  "db_name": "PostgreSQL",
  "query": "SELECT * FROM log_entry ORDER BY timestamp ASC",
  "describe": {
    "columns": [
      {
        "ordinal": 0,
        "name": "timestamp",
        "type_info": "Timestamp"
      },
      {
        "ordinal": 1,
        "name": "server",
        "type_info": "Text"
      },
      {
        "ordinal": 2,
        "name": "transaction_num",
        "type_info": "Int4"
      },
      {
        "ordinal": 3,
        "name": "username",
        "type_info": "Text"
      },
      {
        "ordinal": 4,
        "name": "log",
        "type_info": "Jsonb"
      }
    ],
    "parameters": {
      "Left": []
    },
    "nullable": [
      false,
      false,
      false,
      false,
      false
    ]
  },
  "hash": "cc09091adee059150ddc5dacc2727285ce50359b79029b6e9cf2d54492efd05a"
}
